pytest_subtesthack.py
pytest_subtesthack-0.1.2.dist-info/LICENSE
pytest_subtesthack-0.1.2.dist-info/METADATA
pytest_subtesthack-0.1.2.dist-info/WHEEL
pytest_subtesthack-0.1.2.dist-info/entry_points.txt
pytest_subtesthack-0.1.2.dist-info/top_level.txt
pytest_subtesthack-0.1.2.dist-info/RECORD
