Metadata-Version: 2.1
Name: pytest-subtesthack
Version: 0.1.2
Summary: A hack to explicitly set up and tear down fixtures.
Home-page: https://github.com/untitaker/pytest-subtesthack/
Author: Markus Unterwaditzer
Author-email: markus@unterwaditzer.net
License: Public domain
Platform: UNKNOWN
Requires-Dist: pytest
